{
  "blocks": {
    "event_whenflagclicked1": {
      "opcode": "event_whenflagclicked",
      "next": "event_broadcastandwait1",
      "parent": null,
      "inputs": {},
      "fields": {},
      "shadow": false,
      "topLevel": true,
      "x": 292,
      "y": 222,
      "id": "event_whenflagclicked1"
    },
    "event_broadcastandwait1": {
      "opcode": "event_broadcastandwait",
      "next": null,
      "parent": "event_whenflagclicked1",
      "inputs": {
        "BROADCAST_INPUT": {
          "name": "BROADCAST_INPUT",
          "block": "event_broadcast_menu1",
          "shadow": "event_broadcast_menu1"
        }
      },
      "fields": {},
      "shadow": false,
      "topLevel": false,
      "id": "event_broadcastandwait1"
    },
    "event_broadcastandwait2": {
      "opcode": "event_broadcastandwait",
      "next": null,
      "parent": null,
      "inputs": {
        "BROADCAST_INPUT": {
          "name": "BROADCAST_INPUT",
          "block": "event_broadcast_menu2",
          "shadow": "event_broadcast_menu2"
        }
      },
      "fields": {},
      "shadow": false,
      "topLevel": true,
      "x": 543,
      "y": 187,
      "id": "event_broadcastandwait2"
    },
    "event_broadcast_menu1": {
      "id": "event_broadcast_menu1",
      "next": null,
      "parent": "event_broadcastandwait1",
      "shadow": true,
      "inputs": {},
      "opcode": "event_broadcast_menu",
      "fields": {
        "BROADCAST_OPTION": {
          "name": "BROADCAST_OPTION",
          "value": "GAME begin",
          "id": "X$b7KhkWBuw^}6#}%6`n",
          "variableType": "broadcast_msg"
        }
      },
      "topLevel": false
    },
    "event_broadcast_menu2": {
      "id": "event_broadcast_menu2",
      "next": null,
      "parent": "event_broadcastandwait2",
      "shadow": true,
      "inputs": {},
      "opcode": "event_broadcast_menu",
      "fields": {
        "BROADCAST_OPTION": {
          "name": "BROADCAST_OPTION",
          "value": "GAME main menu",
          "id": "x-9#[KphA@c5tb7!=Ke5",
          "variableType": "broadcast_msg"
        }
      },
      "topLevel": false
    }
  },
  "scripts": [
    "event_whenflagclicked1",
    "event_broadcastandwait2"
  ]
}